funny_hello/__init__.py
funny_hello-0.1.dist-info/DESCRIPTION.rst
funny_hello-0.1.dist-info/METADATA
funny_hello-0.1.dist-info/RECORD
funny_hello-0.1.dist-info/WHEEL
funny_hello-0.1.dist-info/metadata.json
funny_hello-0.1.dist-info/top_level.txt
