Metadata-Version: 2.0
Name: funny-hello
Version: 0.1
Summary: Hello world test packaging
Home-page: http://github.com/storborg/funniest
Author: Flying Circus
Author-email: ar3717@columbia.com
License: UNKNOWN
Platform: UNKNOWN
